common/__init__.py
common/llm/__init__.py
common/llm/client.py
common/notifications/__init__.py
common/notifications/client.py
common/notifications/enums.py
common/notifications/exceptions.py
healthchecker/__init__.py
healthchecker/src/__init__.py
healthchecker/src/__main__.py
healthchecker/src/checker.py
mcp_server/__init__.py
mcp_server/scripts/__init__.py
mcp_server/scripts/mcp_health_check.py
mcp_server/src/__init__.py
mcp_server/src/decorators.py
mcp_server/src/logger.py
mcp_server/src/main.py
mcp_server/src/registry_client.py
mcp_server/src/schemas.py
mcp_server/src/settings.py
mcp_server/src/tools.py
mcp_server/src/llm/__init__.py
mcp_server/src/llm/prompts.py
mcp_server/src/llm/tool_manager.py
mseep_darp_engine-1.0.0.dist-info/licenses/LICENSE
registry/__init__.py
registry/src/__init__.py
registry/src/base_schema.py
registry/src/errors.py
registry/src/logger.py
registry/src/main.py
registry/src/producer.py
registry/src/settings.py
registry/src/types.py
registry/src/database/__init__.py
registry/src/database/session.py
registry/src/database/models/__init__.py
registry/src/database/models/base.py
registry/src/database/models/log.py
registry/src/database/models/server.py
registry/src/database/models/tool.py
registry/src/database/models/mixins/__init__.py
registry/src/database/models/mixins/has_created_at.py
registry/src/database/models/mixins/has_server_id.py
registry/src/database/models/mixins/has_updated_at.py
registry/src/deployments/__init__.py
registry/src/deployments/logs_repository.py
registry/src/deployments/router.py
registry/src/deployments/schemas.py
registry/src/deployments/service.py
registry/src/search/__init__.py
registry/src/search/prompts.py
registry/src/search/schemas.py
registry/src/search/service.py
registry/src/servers/__init__.py
registry/src/servers/repository.py
registry/src/servers/router.py
registry/src/servers/schemas.py
registry/src/servers/service.py
registry/src/validator/__init__.py
registry/src/validator/constants.py
registry/src/validator/prompts.py
mseep_darp_engine-1.0.0.dist-info/METADATA
mseep_darp_engine-1.0.0.dist-info/WHEEL
mseep_darp_engine-1.0.0.dist-info/top_level.txt
mseep_darp_engine-1.0.0.dist-info/RECORD
